loremify/__init__.py
loremify/_paragraph.py
loremify/_sentence.py
loremify/_words.py
loremify-0.0.11.dist-info/LICENSE
loremify-0.0.11.dist-info/METADATA
loremify-0.0.11.dist-info/WHEEL
loremify-0.0.11.dist-info/top_level.txt
loremify-0.0.11.dist-info/RECORD
